biometalib/__init__.py
biometalib/logger.py
biometalib/models.py
biometalib/data/biosample.yaml
biometalib/data/cleaned_fields.yaml
biometalib/data/flybase_example.yaml
biometalib/utils/__init__.py
biometalib/utils/attribute_selector.py
biometalib/utils/initialize_biometa.py
biometalib-0.0.4.dist-info/DESCRIPTION.rst
biometalib-0.0.4.dist-info/METADATA
biometalib-0.0.4.dist-info/RECORD
biometalib-0.0.4.dist-info/WHEEL
biometalib-0.0.4.dist-info/entry_points.txt
biometalib-0.0.4.dist-info/metadata.json
biometalib-0.0.4.dist-info/top_level.txt
