Metadata-Version: 2.0
Name: biometalib
Version: 0.0.4
Summary: A set of helper functions for working with biological metadata from the SRA.
Home-page: https://github.com/jfear/biometalib
Author: Justin Fear
Author-email: justin.m.fear@gmail.com
License: MIT license
Platform: UNKNOWN
Requires-Dist: fuzzywuzzy (>=0.15.0)
Requires-Dist: mongoengine (>=0.11.0)
Requires-Dist: numpy (<=1.13.0)
Requires-Dist: pymongo (>=3.3.0)
Requires-Dist: pytest (>=3.0.5)
Requires-Dist: pytest-runner (>=2.11)
Requires-Dist: pyyaml (>=3.12)
Requires-Dist: ruamel.yaml (<0.15.0)
Requires-Dist: sramongo (>=0.0.2)
